clintermission/__init__.py
clintermission/climenu.py
clintermission-0.3.1.dist-info/LICENSE
clintermission-0.3.1.dist-info/METADATA
clintermission-0.3.1.dist-info/WHEEL
clintermission-0.3.1.dist-info/top_level.txt
clintermission-0.3.1.dist-info/RECORD
