Metadata-Version: 2.1
Name: clintermission
Version: 0.3.1
Summary: Non-fullscreen command-line selection menu
Home-page: https://github.com/sebageek/clintermission
Author: Sebastian Lohff
Author-email: seba@someserver.de
License: Apache-2.0
Keywords: cli,menu
Platform: any
Classifier: Development Status :: 3 - Alpha
Classifier: Intended Audience :: Developers
Classifier: Programming Language :: Python :: 3
Classifier: Programming Language :: Python :: 3.7
Classifier: Programming Language :: Python :: 3.8
Classifier: Programming Language :: Python :: 3.9
Classifier: Programming Language :: Python :: 3.10
Classifier: Programming Language :: Python :: 3.11
Classifier: License :: OSI Approved :: Apache Software License
Requires-Python: >=3.7
License-File: LICENSE
Requires-Dist: prompt-toolkit (>3.0.3)
